atendentepro/README.md
atendentepro/__init__.py
atendentepro/license.py
atendentepro/network.py
atendentepro/agents/__init__.py
atendentepro/agents/answer.py
atendentepro/agents/confirmation.py
atendentepro/agents/escalation.py
atendentepro/agents/feedback.py
atendentepro/agents/flow.py
atendentepro/agents/interview.py
atendentepro/agents/knowledge.py
atendentepro/agents/onboarding.py
atendentepro/agents/triage.py
atendentepro/agents/usage.py
atendentepro/config/__init__.py
atendentepro/config/settings.py
atendentepro/guardrails/__init__.py
atendentepro/guardrails/manager.py
atendentepro/models/__init__.py
atendentepro/models/context.py
atendentepro/models/outputs.py
atendentepro/prompts/__init__.py
atendentepro/prompts/answer.py
atendentepro/prompts/confirmation.py
atendentepro/prompts/escalation.py
atendentepro/prompts/feedback.py
atendentepro/prompts/flow.py
atendentepro/prompts/interview.py
atendentepro/prompts/knowledge.py
atendentepro/prompts/onboarding.py
atendentepro/prompts/triage.py
atendentepro/templates/__init__.py
atendentepro/templates/manager.py
atendentepro/utils/__init__.py
atendentepro/utils/openai_client.py
atendentepro/utils/tracing.py
atendentepro-0.6.5.dist-info/licenses/LICENSE
atendentepro-0.6.5.dist-info/METADATA
atendentepro-0.6.5.dist-info/WHEEL
atendentepro-0.6.5.dist-info/entry_points.txt
atendentepro-0.6.5.dist-info/top_level.txt
atendentepro-0.6.5.dist-info/RECORD
