Metadata-Version: 2.4
Name: atendentepro
Version: 0.6.5
Summary: Framework de orquestração de agentes IA com tom e estilo customizáveis. Integra documentos (RAG), APIs e bancos de dados em uma plataforma inteligente multi-agente.
Author-email: BeMonkAI <contato@monkai.com.br>
Maintainer-email: BeMonkAI <contato@monkai.com.br>
License: Proprietary
Project-URL: Homepage, https://github.com/BeMonkAI/atendentepro
Project-URL: Documentation, https://github.com/BeMonkAI/atendentepro#readme
Project-URL: Repository, https://github.com/BeMonkAI/atendentepro
Project-URL: Issues, https://github.com/BeMonkAI/atendentepro/issues
Project-URL: Changelog, https://github.com/BeMonkAI/atendentepro/blob/main/CHANGELOG.md
Keywords: ai,agents,customer-service,chatbot,openai,multi-agent,atendimento,openai-agents,conversational-ai,rag,triage,handoff,escalation,feedback,knowledge-base,interview
Classifier: Development Status :: 4 - Beta
Classifier: Intended Audience :: Developers
Classifier: License :: Other/Proprietary License
Classifier: Programming Language :: Python :: 3
Classifier: Programming Language :: Python :: 3.9
Classifier: Programming Language :: Python :: 3.10
Classifier: Programming Language :: Python :: 3.11
Classifier: Programming Language :: Python :: 3.12
Classifier: Topic :: Scientific/Engineering :: Artificial Intelligence
Classifier: Topic :: Communications :: Chat
Classifier: Operating System :: OS Independent
Requires-Python: >=3.9
License-File: LICENSE
Requires-Dist: openai-agents<1.0.0,>=0.3.3
Requires-Dist: openai<2.0.0,>=1.107.1
Requires-Dist: pydantic<3.0.0,>=2.0.0
Requires-Dist: PyYAML<7.0,>=6.0
Requires-Dist: python-dotenv<2.0.0,>=1.0.0
Requires-Dist: httpx<1.0.0,>=0.27.0
Provides-Extra: dev
Requires-Dist: pytest<9.0.0,>=7.0.0; extra == "dev"
Requires-Dist: pytest-asyncio<1.0.0,>=0.21.0; extra == "dev"
Requires-Dist: black<25.0.0,>=23.0.0; extra == "dev"
Requires-Dist: isort<6.0.0,>=5.12.0; extra == "dev"
Requires-Dist: mypy<2.0.0,>=1.0.0; extra == "dev"
Provides-Extra: docs
Requires-Dist: mkdocs<2.0.0,>=1.5.0; extra == "docs"
Requires-Dist: mkdocs-material<10.0.0,>=9.0.0; extra == "docs"
Provides-Extra: rag
Requires-Dist: numpy<2.0.0,>=1.24.0; extra == "rag"
Requires-Dist: scikit-learn<2.0.0,>=1.3.0; extra == "rag"
Requires-Dist: PyPDF2<4.0.0,>=3.0.0; extra == "rag"
Requires-Dist: python-docx<2.0.0,>=0.8.11; extra == "rag"
Requires-Dist: python-pptx<1.0.0,>=0.6.21; extra == "rag"
Requires-Dist: PyMuPDF<2.0.0,>=1.23.0; extra == "rag"
Provides-Extra: tracing
Requires-Dist: monkai-trace<1.0.0,>=0.2.9; extra == "tracing"
Provides-Extra: azure
Requires-Dist: opentelemetry-sdk<2.0.0,>=1.20.0; extra == "azure"
Requires-Dist: azure-monitor-opentelemetry-exporter<2.0.0,>=1.0.0; extra == "azure"
Provides-Extra: all
Requires-Dist: atendentepro[azure,dev,docs,rag,tracing]; extra == "all"
Dynamic: license-file
